[{"match_id":6130494024,"player_slot":132,"radiant_win":true,"duration":7199,"game_mode":3,"lobby_type":7,"hero_id":87,"start_time":1628690281,"version":21,"kills":20,"deaths":20,"assists":14,"skill":2,"leaver_status":0,"party_size":2},{"match_id":6130393901,"player_slot":129,"radiant_win":false,"duration":2749,"game_mode":22,"lobby_type":7,"hero_id":58,"start_time":1628686600,"version":21,"kills":2,"deaths":4,"assists":14,"skill":null,"leaver_status":0,"party_size":2},{"match_id":6129087851,"player_slot":129,"radiant_win":false,"duration":1750,"game_mode":22,"lobby_type":7,"hero_id":67,"start_time":1628605045,"version":21,"kills":4,"deaths":0,"assists":11,"skill":1,"leaver_status":0,"party_size":2},{"match_id":6129021352,"player_slot":4,"radiant_win":false,"duration":1729,"game_mode":22,"lobby_type":7,"hero_id":1,"start_time":1628602610,"version":21,"kills":1,"deaths":5,"assists":3,"skill":1,"leaver_status":0,"party_size":2},{"match_id":6127509196,"player_slot":129,"radiant_win":true,"duration":3541,"game_mode":22,"lobby_type":7,"hero_id":2,"start_time":1628513429,"version":21,"kills":6,"deaths":18,"assists":10,"skill":null,"leaver_status":0,"party_size":2}]
